oauth2cli/VERSION
oauth2cli/__init__.py
oauth2cli-1.0.3.dist-info/LICENSE
oauth2cli-1.0.3.dist-info/METADATA
oauth2cli-1.0.3.dist-info/WHEEL
oauth2cli-1.0.3.dist-info/entry_points.txt
oauth2cli-1.0.3.dist-info/top_level.txt
oauth2cli-1.0.3.dist-info/RECORD
