Metadata-Version: 2.1
Name: oauth2cli
Version: 1.0.3
Summary: Generic OAuth 2.0 command-line utility to retrieve access tokens. Uses Python standard library!
Home-page: https://github.com/aerohstudios/oauth2cli
Author: Shiv Deepak Muddada
Author-email: shiv@aeroh.org
License: Apache Software License (http://www.apache.org/licenses/LICENSE-2.0)
Platform: any
Classifier: Development Status :: 4 - Beta
Classifier: Environment :: Console
Classifier: Intended Audience :: Developers
Classifier: License :: OSI Approved :: Apache Software License
Classifier: Operating System :: MacOS
Classifier: Operating System :: Microsoft :: Windows
Classifier: Operating System :: POSIX
Classifier: Operating System :: Unix
Classifier: Programming Language :: Python :: 3
Classifier: Topic :: Internet :: WWW/HTTP :: HTTP Servers
Classifier: Topic :: Internet :: WWW/HTTP :: Session
Classifier: Topic :: Software Development
Requires-Python: >=3.0
License-File: LICENSE
